{
  "schema_id": "rates.api_record.v1",
  "schema_version": 1,
  "dataset_id": "treasury-yield-curve",
  "dataset_path": "treasury/treasury-yield-curve",
  "record_key": "1994-01-12",
  "canonical_record_path": "treasury/treasury-yield-curve/by-year/1994-treasury-yield-curve.json",
  "canonical_manifest_path": "treasury/treasury-yield-curve/manifest.json",
  "record": {
    "date": "1994-01-12",
    "par_yields_basis_points": [
      null,
      null,
      null,
      302,
      null,
      321,
      347,
      405,
      436,
      495,
      529,
      560,
      626,
      617
    ]
  }
}
