{
  "schema_id": "rates.api_record.v1",
  "schema_version": 1,
  "dataset_id": "treasury-yield-curve",
  "dataset_path": "treasury/treasury-yield-curve",
  "record_key": "2008-10-01",
  "canonical_record_path": "treasury/treasury-yield-curve/by-year/2008-treasury-yield-curve.json",
  "canonical_manifest_path": "treasury/treasury-yield-curve/manifest.json",
  "record": {
    "date": "2008-10-01",
    "par_yields_basis_points": [
      66,
      null,
      null,
      85,
      null,
      149,
      172,
      182,
      212,
      287,
      329,
      377,
      433,
      422
    ]
  }
}
