{
  "schema_id": "rates.api_record.v1",
  "schema_version": 1,
  "dataset_id": "treasury-yield-curve",
  "dataset_path": "treasury/treasury-yield-curve",
  "record_key": "2016-03-28",
  "canonical_record_path": "treasury/treasury-yield-curve/by-year/2016-treasury-yield-curve.json",
  "canonical_manifest_path": "treasury/treasury-yield-curve/manifest.json",
  "record": {
    "date": "2016-03-28",
    "par_yields_basis_points": [
      19,
      null,
      null,
      29,
      null,
      49,
      65,
      89,
      104,
      137,
      168,
      189,
      226,
      266
    ]
  }
}
